model_parallelism/__init__.py
model_parallelism-0.1.0.dist-info/LICENSE
model_parallelism-0.1.0.dist-info/METADATA
model_parallelism-0.1.0.dist-info/WHEEL
model_parallelism-0.1.0.dist-info/top_level.txt
model_parallelism-0.1.0.dist-info/RECORD
