Metadata-Version: 2.1
Name: model-parallelism
Version: 0.1.0
Summary: A simple wrapper around DeepSpeed for model parallelism.
Home-page: https://github.com/samuelstevens/model_parallelism
Author: Samuel Stevens
Author-email: samuel.robert.stevens@gmail.com
License: UNKNOWN
Project-URL: Bug Tracker, https://github.com/samuelstevens/model_parallelism/issues
Platform: UNKNOWN
Classifier: Programming Language :: Python :: 3
Classifier: License :: OSI Approved :: MIT License
Classifier: Operating System :: OS Independent
Requires-Python: >=3.6
License-File: LICENSE
